russh-0.5.0.dist-info/METADATA
russh-0.5.0.dist-info/WHEEL
russh-0.5.0.dist-info/license_files/LICENSE
russh.libs/libssl-c9364493.so.3
russh.libs/libcrypto-fe7cdb62.so.3
russh/__init__.py
russh/__init__.pyi
russh/py.typed
russh/russh.abi3.so
russh-0.5.0.dist-info/RECORD
