Metadata-Version: 2.1
Name: russh
Version: 0.5.0
Classifier: Programming Language :: Rust
Classifier: Programming Language :: Python
Classifier: Programming Language :: Python :: 3
Classifier: Programming Language :: Python :: 3 :: Only
Classifier: Programming Language :: Python :: 3.7
Classifier: Programming Language :: Python :: 3.8
Classifier: Programming Language :: Python :: 3.9
Classifier: Programming Language :: Python :: 3.10
Classifier: Programming Language :: Python :: 3.11
Classifier: Programming Language :: Python :: 3.12
Classifier: Programming Language :: Python :: 3.13
Classifier: Programming Language :: Python :: Implementation
Classifier: License :: OSI Approved :: MIT License
Classifier: Operating System :: Microsoft :: Windows
Classifier: Operating System :: MacOS
Classifier: Operating System :: POSIX :: Linux
Classifier: Intended Audience :: Developers
License-File: LICENSE
Keywords: pyo3,python,ssh
Author: Nikhil Prabhu <nikhilprabhu98@gmail.com>
Author-email: Nikhil Prabhu <nikhilprabhu98@gmail.com>
License: MIT
Requires-Python: >=3.7
Project-URL: Source Code, https://github.com/nikhil-prabhu/russh
